qupac/__init__.py
qupac/ai_agent.py
qupac/cli.py
qupac/executor.py
qupac/grammar.lark
qupac/parser.py
qupac/transpiler.py
qupac-0.2.0.dist-info/licenses/LICENSE
qupac-0.2.0.dist-info/METADATA
qupac-0.2.0.dist-info/WHEEL
qupac-0.2.0.dist-info/entry_points.txt
qupac-0.2.0.dist-info/top_level.txt
qupac-0.2.0.dist-info/RECORD
