Metadata-Version: 2.4
Name: qupac
Version: 0.2.0
Summary: Qupac (Quantum Python Abstraction Compiler): lightweight language for quantum circuits transpiled to Qiskit 2.x
Author: Amol Yadav
License: MIT License
Project-URL: Homepage, https://pypi.org/project/qupac/
Project-URL: Repository, https://example.com/your-repo
Keywords: quantum,qiskit,dsl,compiler,transpiler
Classifier: Programming Language :: Python
Classifier: Programming Language :: Python :: 3
Classifier: Programming Language :: Python :: 3 :: Only
Classifier: Programming Language :: Python :: 3.9
Classifier: Programming Language :: Python :: 3.10
Classifier: Programming Language :: Python :: 3.11
Classifier: License :: OSI Approved :: MIT License
Classifier: Operating System :: OS Independent
Classifier: Topic :: Scientific/Engineering
Classifier: Topic :: Software Development :: Compilers
Requires-Python: >=3.9
License-File: LICENSE
Requires-Dist: lark==1.3.0
Requires-Dist: qiskit==2.2.1
Requires-Dist: qiskit-aer==0.17.2
Provides-Extra: dev
Requires-Dist: ruff>=0.6; extra == "dev"
Requires-Dist: mypy>=1.10; extra == "dev"
Requires-Dist: pytest>=8.0; extra == "dev"
Requires-Dist: build>=1.2; extra == "dev"
Dynamic: license-file
